skale_checks/__init__.py
skale_checks/requirements.yaml
skale_checks/adapters/__init__.py
skale_checks/adapters/connectors.py
skale_checks/adapters/watchdog.py
skale_checks/checks/__init__.py
skale_checks/checks/base.py
skale_checks/checks/node.py
skale_checks/checks/types.py
skale_checks/checks/utils.py
skale_checks/checks/watchdog.py
skale_checks-1.0.dist-info/LICENSE
skale_checks-1.0.dist-info/METADATA
skale_checks-1.0.dist-info/WHEEL
skale_checks-1.0.dist-info/top_level.txt
skale_checks-1.0.dist-info/RECORD
