Metadata-Version: 2.1
Name: skale-checks
Version: 1.0
Summary: Checks for SKALE infrastructure
Home-page: https://github.com/skalenetwork/skale-checks
Author: SKALE Labs
Author-email: support@skalelabs.com
Keywords: skale,checks
Classifier: Development Status :: 5 - Production/Stable
Classifier: Intended Audience :: Developers
Classifier: License :: OSI Approved :: GNU Affero General Public License v3 or later (AGPLv3+)
Classifier: Natural Language :: English
Classifier: Programming Language :: Python :: 3.7
Requires-Python: >=3.7,<4
License-File: LICENSE
Requires-Dist: skale.py==6.2b0
Requires-Dist: elasticsearch==7.12.0
Provides-Extra: dev
Requires-Dist: flake8==3.7.9; extra == "dev"
Requires-Dist: twine==3.1.1; extra == "dev"
Provides-Extra: linter
Requires-Dist: flake8==3.7.9; extra == "linter"
